LICENSE
MANIFEST.in
README.md
setup.cfg
setup.py
frodocs/__init__.py
frodocs/__main__.py
frodocs/exceptions.py
frodocs/plugins.py
frodocs/theme.py
frodocs.egg-info/PKG-INFO
frodocs.egg-info/SOURCES.txt
frodocs.egg-info/dependency_links.txt
frodocs.egg-info/entry_points.txt
frodocs.egg-info/not-zip-safe
frodocs.egg-info/requires.txt
frodocs.egg-info/top_level.txt
frodocs/commands/__init__.py
frodocs/commands/build.py
frodocs/commands/gh_deploy.py
frodocs/commands/new.py
frodocs/commands/serve.py
frodocs/config/__init__.py
frodocs/config/base.py
frodocs/config/config_options.py
frodocs/config/defaults.py
frodocs/contrib/__init__.py
frodocs/contrib/search/__init__.py
frodocs/contrib/search/prebuild-index.js
frodocs/contrib/search/search_index.py
frodocs/contrib/search/lunr-language/lunr.ar.js
frodocs/contrib/search/lunr-language/lunr.da.js
frodocs/contrib/search/lunr-language/lunr.de.js
frodocs/contrib/search/lunr-language/lunr.du.js
frodocs/contrib/search/lunr-language/lunr.es.js
frodocs/contrib/search/lunr-language/lunr.fi.js
frodocs/contrib/search/lunr-language/lunr.fr.js
frodocs/contrib/search/lunr-language/lunr.hu.js
frodocs/contrib/search/lunr-language/lunr.it.js
frodocs/contrib/search/lunr-language/lunr.ja.js
frodocs/contrib/search/lunr-language/lunr.jp.js
frodocs/contrib/search/lunr-language/lunr.multi.js
frodocs/contrib/search/lunr-language/lunr.nl.js
frodocs/contrib/search/lunr-language/lunr.no.js
frodocs/contrib/search/lunr-language/lunr.pt.js
frodocs/contrib/search/lunr-language/lunr.ro.js
frodocs/contrib/search/lunr-language/lunr.ru.js
frodocs/contrib/search/lunr-language/lunr.stemmer.support.js
frodocs/contrib/search/lunr-language/lunr.sv.js
frodocs/contrib/search/lunr-language/lunr.th.js
frodocs/contrib/search/lunr-language/lunr.tr.js
frodocs/contrib/search/lunr-language/lunr.vi.js
frodocs/contrib/search/templates/search/lunr.js
frodocs/contrib/search/templates/search/main.js
frodocs/contrib/search/templates/search/worker.js
frodocs/structure/__init__.py
frodocs/structure/files.py
frodocs/structure/nav.py
frodocs/structure/pages.py
frodocs/structure/toc.py
frodocs/templates/sitemap.xml
frodocs/tests/__init__.py
frodocs/tests/base.py
frodocs/tests/build_tests.py
